Workbook

Sheet Assumptions
A1: DCF Valuation Model - Assumptions
A3: Company Info
A4: Company Name | B4: TCS
A5: Current Market Price (Rs) | B5: 3200
A7: Base Financials (Latest Actual Year)
A8: Base Revenue (Rs Cr) | B8: 240893
A9: Net Debt (Rs Cr) [negative = net cash] | B9: -22400
A10: Shares Outstanding (Cr) | B10: 365
A12: Forecast Assumptions
A13: Revenue Growth Rate (%) | B13: 0.08
A14: EBIT Margin (%) | B14: 0.26
A15: Tax Rate (%) | B15: 0.25
A16: D&A (% of Revenue) | B16: 0.03
A17: Capex (% of Revenue) | B17: 0.05
A18: Change in NWC (% of Revenue) | B18: 0.01
A19: Forecast Years | B19: 5
A21: WACC Inputs
A22: Risk Free Rate (%) | B22: 0.068
A23: Beta | B23: 0.95
A24: Expected Market Return (%) | B24: 0.115
A25: Pre-tax Cost of Debt (%) | B25: 0.075
A26: Market Capitalization (Rs Cr) | B26: 1160000
A27: Total Debt (Rs Cr) | B27: 8000
A29: Terminal Value
A30: Terminal Growth Rate (%) | B30: 0.04
A32: Yellow cells = key assumptions you should adjust. Blue text = editable input.

Sheet WACC
A1: WACC - Discount Rate Calculation
A3: Cost of Equity (CAPM)
A4: Risk Free Rate | B4: =Assumptions!B22 -> 0.068
A5: Beta | B5: =Assumptions!B23 -> 0.95
A6: Expected Market Return | B6: =Assumptions!B24 -> 0.115
A7: Cost of Equity (Ke) | B7: =B4+B5*(B6-B4) -> 0.11265
A9: Cost of Debt
A10: Pre-tax Cost of Debt | B10: =Assumptions!B25 -> 0.075
A11: Tax Rate | B11: =Assumptions!B15 -> 0.25
A12: After-tax Cost of Debt | B12: =B10*(1-B11) -> 0.05625
A14: Capital Structure Weights
A15: Market Cap (Equity, E) | B15: =Assumptions!B26 -> 1160000
A16: Total Debt (D) | B16: =Assumptions!B27 -> 8000
A17: Equity Weight E/(D+E) | B17: =B15/(B15+B16) -> 0.99315068
A18: Debt Weight D/(D+E) | B18: =B16/(B15+B16) -> 0.0068493151
A20: Final WACC
A21: WACC = E/(D+E) x Ke + D/(D+E) x Kd x (1-T) | B21: =B17*B7+B18*B12 -> 0.1122637

Sheet Forecast
A1: 5-Year Forecast - Revenue to FCFF
A3: Period
A4: Metric | B4: Year 1 | C4: Year 2 | D4: Year 3 | E4: Year 4 | F4: Year 5
A5: Revenue | B5: =Assumptions!$B$8*(1+Assumptions!$B$13) -> 260164.44 | C5: =B5*(1+Assumptions!$B$13) -> 280977.6 | D5: =C5*(1+Assumptions!$B$13) -> 303455.8 | E5: =D5*(1+Assumptions!$B$13) -> 327732.27 | F5: =E5*(1+Assumptions!$B$13) -> 353950.85
A6: EBIT | B6: =B5*Assumptions!$B$14 -> 67642.754 | C6: =C5*Assumptions!$B$14 -> 73054.175 | D6: =D5*Assumptions!$B$14 -> 78898.509 | E6: =E5*Assumptions!$B$14 -> 85210.389 | F6: =F5*Assumptions!$B$14 -> 92027.221
A7: NOPAT | B7: =B6*(1-Assumptions!$B$15) -> 50732.066 | C7: =C6*(1-Assumptions!$B$15) -> 54790.631 | D7: =D6*(1-Assumptions!$B$15) -> 59173.882 | E7: =E6*(1-Assumptions!$B$15) -> 63907.792 | F7: =F6*(1-Assumptions!$B$15) -> 69020.415
A8: (+) D&A | B8: =B5*Assumptions!$B$16 -> 7804.9332 | C8: =C5*Assumptions!$B$16 -> 8429.3279 | D8: =D5*Assumptions!$B$16 -> 9103.6741 | E8: =E5*Assumptions!$B$16 -> 9831.968 | F8: =F5*Assumptions!$B$16 -> 10618.525
A9: (-) Capex | B9: =B5*Assumptions!$B$17 -> 13008.222 | C9: =C5*Assumptions!$B$17 -> 14048.88 | D9: =D5*Assumptions!$B$17 -> 15172.79 | E9: =E5*Assumptions!$B$17 -> 16386.613 | F9: =F5*Assumptions!$B$17 -> 17697.542
A10: (-) Change in NWC | B10: =B5*Assumptions!$B$18 -> 2601.6444 | C10: =C5*Assumptions!$B$18 -> 2809.776 | D10: =D5*Assumptions!$B$18 -> 3034.558 | E10: =E5*Assumptions!$B$18 -> 3277.3227 | F10: =F5*Assumptions!$B$18 -> 3539.5085
A11: FCFF | B11: =B7+B8-B9-B10 -> 42927.133 | C11: =C7+C8-C9-C10 -> 46361.303 | D11: =D7+D8-D9-D10 -> 50070.207 | E11: =E7+E8-E9-E10 -> 54075.824 | F11: =F7+F8-F9-F10 -> 58401.89
A12: Discount Factor | B12: =1/(1+WACC!$B$21)^1 -> 0.89906737 | C12: =1/(1+WACC!$B$21)^2 -> 0.80832214 | D12: =1/(1+WACC!$B$21)^3 -> 0.72673606 | E12: =1/(1+WACC!$B$21)^4 -> 0.65338468 | F12: =1/(1+WACC!$B$21)^5 -> 0.58743685
A13: PV of FCFF | B13: =B11*B12 -> 38594.384 | C13: =C11*C12 -> 37474.868 | D13: =D11*D12 -> 36387.825 | E13: =E11*E12 -> 35332.315 | F13: =F11*F12 -> 34307.422

Sheet DCF Valuation
A1: DCF Valuation Summary
A3: Present Value of Cash Flows
A4: Sum of PV of FCFF (Years 1-5) | B4: =SUM(Forecast!B13:F13) -> 182096.81
A6: Terminal Value
A7: Final Year FCFF | B7: =Forecast!F11 -> 58401.89
A8: Terminal Growth Rate | B8: =Assumptions!B30 -> 0.04
A9: WACC | B9: =WACC!B21 -> 0.1122637
A10: Terminal Value = FCFF5 x (1+g) / (WACC-g) | B10: =B7*(1+B8)/(B9-B8) -> 840504.52
A11: PV of Terminal Value | B11: =B10/(1+B9)^Assumptions!B19 -> 493743.33
A13: Enterprise Value -> Equity Value
A14: Enterprise Value | B14: =B4+B11 -> 675840.14
A15: (-) Net Debt | B15: =Assumptions!B9 -> -22400
A16: Equity Value | B16: =B14-B15 -> 698240.14
A17: / Shares Outstanding | B17: =Assumptions!B10 -> 365
A19: Intrinsic Value
A20: Intrinsic Value per Share (Rs) | B20: =B16/B17 -> 1912.9867
A21: Current Market Price (Rs) | B21: =Assumptions!B5 -> 3200
A22: Upside / (Downside) % | B22: =(B20-B21)/B21 -> -0.40219166
A24: Verdict | B24: =IF(B22>0,"Potentially Undervalued","Potentially Overvalued") -> Potentially Overvalued
A26: Not a guaranteed Buy/Sell signal - DCF output is highly sensitive to assumptions. See the Sensitivity sheet.

Sheet Sensitivity
A1: Sensitivity - Intrinsic Value per Share
A3: Rows = WACC, Columns = Terminal Growth Rate
A4: WACC \ Growth | B4: =Assumptions!$B$30+(-0.01) -> 0.03 | C4: =Assumptions!$B$30+(-0.005) -> 0.035 | D4: =Assumptions!$B$30+(0) -> 0.04 | E4: =Assumptions!$B$30+(0.005) -> 0.045 | F4: =Assumptions!$B$30+(0.01) -> 0.05
A5: =WACC!$B$21+(-0.01) -> 0.1022637 | B5: =(SUMPRODUCT(Forecast!$B$11:$F$11,1/(1+$A5)^{1,2,3,4,5})+((Forecast!$F$11*(1+B$4))/($A5-B$4))/(1+$A5)^Assumptions!$B$19-Assumptions!$B$9)/Assumptions!$B$10 -> 1975.3347 | C5: =(SUMPRODUCT(Forecast!$B$11:$F$11,1/(1+$A5)^{1,2,3,4,5})+((Forecast!$F$11*(1+C$4))/($A5-C$4))/(1+$A5)^Assumptions!$B$19-Assumptions!$B$9)/Assumptions!$B$10 -> 2086.8312 | D5: =(SUMPRODUCT(Forecast!$B$11:$F$11,1/(1+$A5)^{1,2,3,4,5})+((Forecast!$F$11*(1+D$4))/($A5-D$4))/(1+$A5)^Assumptions!$B$19-Assumptions!$B$9)/Assumptions!$B$10 -> 2216.2348 | E5: =(SUMPRODUCT(Forecast!$B$11:$F$11,1/(1+$A5)^{1,2,3,4,5})+((Forecast!$F$11*(1+E$4))/($A5-E$4))/(1+$A5)^Assumptions!$B$19-Assumptions!$B$9)/Assumptions!$B$10 -> 2368.2363 | F5: =(SUMPRODUCT(Forecast!$B$11:$F$11,1/(1+$A5)^{1,2,3,4,5})+((Forecast!$F$11*(1+F$4))/($A5-F$4))/(1+$A5)^Assumptions!$B$19-Assumptions!$B$9)/Assumptions!$B$10 -> 2549.3213
A6: =WACC!$B$21+(-0.005) -> 0.1072637 | B6: =(SUMPRODUCT(Forecast!$B$11:$F$11,1/(1+$A6)^{1,2,3,4,5})+((Forecast!$F$11*(1+B$4))/($A6-B$4))/(1+$A6)^Assumptions!$B$19-Assumptions!$B$9)/Assumptions!$B$10 -> 1848.495 | C6: =(SUMPRODUCT(Forecast!$B$11:$F$11,1/(1+$A6)^{1,2,3,4,5})+((Forecast!$F$11*(1+C$4))/($A6-C$4))/(1+$A6)^Assumptions!$B$19-Assumptions!$B$9)/Assumptions!$B$10 -> 1943.8194 | D6: =(SUMPRODUCT(Forecast!$B$11:$F$11,1/(1+$A6)^{1,2,3,4,5})+((Forecast!$F$11*(1+D$4))/($A6-D$4))/(1+$A6)^Assumptions!$B$19-Assumptions!$B$9)/Assumptions!$B$10 -> 2053.3155 | E6: =(SUMPRODUCT(Forecast!$B$11:$F$11,1/(1+$A6)^{1,2,3,4,5})+((Forecast!$F$11*(1+E$4))/($A6-E$4))/(1+$A6)^Assumptions!$B$19-Assumptions!$B$9)/Assumptions!$B$10 -> 2180.3975 | F6: =(SUMPRODUCT(Forecast!$B$11:$F$11,1/(1+$A6)^{1,2,3,4,5})+((Forecast!$F$11*(1+F$4))/($A6-F$4))/(1+$A6)^Assumptions!$B$19-Assumptions!$B$9)/Assumptions!$B$10 -> 2329.672
A7: =WACC!$B$21+(0) -> 0.1122637 | B7: =(SUMPRODUCT(Forecast!$B$11:$F$11,1/(1+$A7)^{1,2,3,4,5})+((Forecast!$F$11*(1+B$4))/($A7-B$4))/(1+$A7)^Assumptions!$B$19-Assumptions!$B$9)/Assumptions!$B$10 -> 1737.1237 | C7: =(SUMPRODUCT(Forecast!$B$11:$F$11,1/(1+$A7)^{1,2,3,4,5})+((Forecast!$F$11*(1+C$4))/($A7-C$4))/(1+$A7)^Assumptions!$B$19-Assumptions!$B$9)/Assumptions!$B$10 -> 1819.3648 | D7: =(SUMPRODUCT(Forecast!$B$11:$F$11,1/(1+$A7)^{1,2,3,4,5})+((Forecast!$F$11*(1+D$4))/($A7-D$4))/(1+$A7)^Assumptions!$B$19-Assumptions!$B$9)/Assumptions!$B$10 -> 1912.9867 | E7: =(SUMPRODUCT(Forecast!$B$11:$F$11,1/(1+$A7)^{1,2,3,4,5})+((Forecast!$F$11*(1+E$4))/($A7-E$4))/(1+$A7)^Assumptions!$B$19-Assumptions!$B$9)/Assumptions!$B$10 -> 2020.5272 | F7: =(SUMPRODUCT(Forecast!$B$11:$F$11,1/(1+$A7)^{1,2,3,4,5})+((Forecast!$F$11*(1+F$4))/($A7-F$4))/(1+$A7)^Assumptions!$B$19-Assumptions!$B$9)/Assumptions!$B$10 -> 2145.3395
A8: =WACC!$B$21+(0.005) -> 0.1172637 | B8: =(SUMPRODUCT(Forecast!$B$11:$F$11,1/(1+$A8)^{1,2,3,4,5})+((Forecast!$F$11*(1+B$4))/($A8-B$4))/(1+$A8)^Assumptions!$B$19-Assumptions!$B$9)/Assumptions!$B$10 -> 1638.5608 | C8: =(SUMPRODUCT(Forecast!$B$11:$F$11,1/(1+$A8)^{1,2,3,4,5})+((Forecast!$F$11*(1+C$4))/($A8-C$4))/(1+$A8)^Assumptions!$B$19-Assumptions!$B$9)/Assumptions!$B$10 -> 1710.0828 | D8: =(SUMPRODUCT(Forecast!$B$11:$F$11,1/(1+$A8)^{1,2,3,4,5})+((Forecast!$F$11*(1+D$4))/($A8-D$4))/(1+$A8)^Assumptions!$B$19-Assumptions!$B$9)/Assumptions!$B$10 -> 1790.8616 | E8: =(SUMPRODUCT(Forecast!$B$11:$F$11,1/(1+$A8)^{1,2,3,4,5})+((Forecast!$F$11*(1+E$4))/($A8-E$4))/(1+$A8)^Assumptions!$B$19-Assumptions!$B$9)/Assumptions!$B$10 -> 1882.8188 | F8: =(SUMPRODUCT(Forecast!$B$11:$F$11,1/(1+$A8)^{1,2,3,4,5})+((Forecast!$F$11*(1+F$4))/($A8-F$4))/(1+$A8)^Assumptions!$B$19-Assumptions!$B$9)/Assumptions!$B$10 -> 1988.4471
A9: =WACC!$B$21+(0.01) -> 0.1222637 | B9: =(SUMPRODUCT(Forecast!$B$11:$F$11,1/(1+$A9)^{1,2,3,4,5})+((Forecast!$F$11*(1+B$4))/($A9-B$4))/(1+$A9)^Assumptions!$B$19-Assumptions!$B$9)/Assumptions!$B$10 -> 1550.7231 | C9: =(SUMPRODUCT(Forecast!$B$11:$F$11,1/(1+$A9)^{1,2,3,4,5})+((Forecast!$F$11*(1+C$4))/($A9-C$4))/(1+$A9)^Assumptions!$B$19-Assumptions!$B$9)/Assumptions!$B$10 -> 1613.3642 | D9: =(SUMPRODUCT(Forecast!$B$11:$F$11,1/(1+$A9)^{1,2,3,4,5})+((Forecast!$F$11*(1+D$4))/($A9-D$4))/(1+$A9)^Assumptions!$B$19-Assumptions!$B$9)/Assumptions!$B$10 -> 1683.6201 | E9: =(SUMPRODUCT(Forecast!$B$11:$F$11,1/(1+$A9)^{1,2,3,4,5})+((Forecast!$F$11*(1+E$4))/($A9-E$4))/(1+$A9)^Assumptions!$B$19-Assumptions!$B$9)/Assumptions!$B$10 -> 1762.969 | F9: =(SUMPRODUCT(Forecast!$B$11:$F$11,1/(1+$A9)^{1,2,3,4,5})+((Forecast!$F$11*(1+F$4))/($A9-F$4))/(1+$A9)^Assumptions!$B$19-Assumptions!$B$9)/Assumptions!$B$10 -> 1853.2983
A11: Note: cells where WACC <= Growth will show an error - not a valid combination.
